verity_import/__init__.py
verity_import/filtersets.py
verity_import/forms.py
verity_import/models.py
verity_import/navigation.py
verity_import/search.py
verity_import/tables.py
verity_import/urls.py
verity_import/views.py
verity_import/api/__init__.py
verity_import/api/serializers.py
verity_import/api/urls.py
verity_import/api/views.py
verity_import/migrations/0001_initial.py
verity_import/migrations/0002_alter_veritysource_options_and_more.py
verity_import/migrations/__init__.py
verity_import/templates/verity_import/sync_result.html
verity_import/templates/verity_import/veritylastsynctime.html
verity_import/templates/verity_import/veritysource.html
verity_import/templates/verity_import/veritysourcelogin.html
verity_import-1.0.1.dist-info/licenses/LICENSE
verity_import-1.0.1.dist-info/METADATA
verity_import-1.0.1.dist-info/WHEEL
verity_import-1.0.1.dist-info/top_level.txt
verity_import-1.0.1.dist-info/RECORD
