Metadata-Version: 2.4
Name: verity-import
Version: 1.0.1
Summary: Import a Verity system into Netbox
License-File: LICENSE
Dynamic: license-file
Dynamic: summary
